mfplus/__init__.py
mfplus/mfpconvert.py
mfplus/mfpreqs.py
mfplus-1.0.0.dist-info/METADATA
mfplus-1.0.0.dist-info/WHEEL
mfplus-1.0.0.dist-info/top_level.txt
mfplus-1.0.0.dist-info/RECORD
